{
  "config": {
    "title": "Metsnip UI",
    "description": "My awesome app using docz",
    "menu": [],
    "ordering": "descending",
    "version": "1.0.0",
    "repository": null,
    "native": false,
    "codeSandbox": true,
    "themeConfig": {},
    "typescript": true
  },
  "entries": {
    "src/components/Button/index.mdx": {
      "name": "Button",
      "menu": "Components",
      "id": "a08e664b64d63394cab05b2e5d624522",
      "filepath": "src/components/Button/index.mdx",
      "link": null,
      "slug": "src-components-button-index",
      "route": "/src-components-button-index",
      "order": 0,
      "headings": [
        {
          "depth": 1,
          "slug": "button",
          "value": "Button"
        },
        {
          "depth": 3,
          "slug": "best-practices",
          "value": "Best practices"
        },
        {
          "depth": 2,
          "slug": "basic-usage",
          "value": "Basic usage"
        },
        {
          "depth": 2,
          "slug": "with-different-sizes",
          "value": "With different sizes"
        },
        {
          "depth": 2,
          "slug": "with-different-colors",
          "value": "With different colors"
        },
        {
          "depth": 2,
          "slug": "outlined",
          "value": "Outlined"
        },
        {
          "depth": 2,
          "slug": "properties",
          "value": "Properties"
        }
      ]
    }
  }
}